autoact/__init__.py
autoact/autoact.py
autoact-0.0.3.dist-info/METADATA
autoact-0.0.3.dist-info/WHEEL
autoact-0.0.3.dist-info/licenses/LICENSE
autoact-0.0.3.dist-info/RECORD
