Metadata-Version: 2.1
Name: autoact
Version: 0.0.3
Summary: The  SDK of AutoAct
Project-URL: Homepage, http://szhypercasual.com
Author-email: zhou yongqiang <zhouyongqiang2706@gmail.com>
License: MIT License
License-File: LICENSE
Keywords: AutoAct
Requires-Python: >=2.0
Requires-Dist: requests
